emewscreator/__init__.py
emewscreator/__main__.py
emewscreator/cli.py
emewscreator/generate.py
emewscreator/util.py
emewscreator/templates/common/hooks/post_gen_project.py
emewscreator/templates/common/j2s/common/cfg.j2
emewscreator/templates/common/j2s/common/machine.j2
emewscreator/templates/common/j2s/common/run_model_5_args_sh.j2
emewscreator/templates/common/j2s/common/run_model_sh.j2
emewscreator/templates/common/j2s/common/submission_args.j2
emewscreator/templates/common/j2s/common/submission_job_exports.j2
emewscreator/templates/common/j2s/common/submission_prefix.j2
emewscreator/templates/common/j2s/common/submission_python_paths.j2
emewscreator/templates/common/j2s/common/submission_r_paths.j2
emewscreator/templates/common/j2s/common/swift_utils.j2
emewscreator/templates/common/j2s/eq/calc_agg_model_result_placeholder.j2
emewscreator/templates/common/j2s/eq/calc_model_result_placeholder.j2
emewscreator/templates/common/j2s/eq/eq_globals.j2
emewscreator/templates/common/j2s/eq/eq_imports.j2
emewscreator/templates/common/j2s/eq/eq_loop.j2
emewscreator/templates/common/j2s/eq/eq_main.j2
emewscreator/templates/common/j2s/eq/eq_obj.j2
emewscreator/templates/common/j2s/eq/eq_submission_prefix.j2
emewscreator/templates/common/j2s/eq/submission.j2
emewscreator/templates/common/j2s/eqpy/eq_start.j2
emewscreator/templates/common/j2s/eqr/eq_start.j2
emewscreator/templates/common/j2s/eqsql/eqsql_submission.j2
emewscreator/templates/common/j2s/eqsql/eqsql_submission_prefix.j2
emewscreator/templates/common/j2s/sweep/submission.j2
emewscreator/templates/emews/hooks/post_gen_project.py
emewscreator/templates/emews/{{cookiecutter.emews_root_directory}}/README.md
emewscreator/templates/emews/{{cookiecutter.emews_root_directory}}/gitignore.txt
emewscreator/templates/emews/{{cookiecutter.emews_root_directory}}/R/.retain
emewscreator/templates/emews/{{cookiecutter.emews_root_directory}}/R/test/.retain
emewscreator-1.4.2.dist-info/LICENSE
emewscreator-1.4.2.dist-info/METADATA
emewscreator-1.4.2.dist-info/WHEEL
emewscreator-1.4.2.dist-info/entry_points.txt
emewscreator-1.4.2.dist-info/top_level.txt
emewscreator-1.4.2.dist-info/RECORD
