Metadata-Version: 2.1
Name: emewscreator
Version: 1.4.2
Summary: emewscreator simplifies the creation of emews workflows through the use of templates
Home-page: https://github.com/emews/emews-project-creator
Author: Nick Collier
Author-email: ncollier@anl.gov
Maintainer: Nick Collier
Maintainer-email: ncollier@anl.gov
License: BSD 3-Clause License
Project-URL: Bug Tracker, https://github.com/emews/emews-project-creator/issues
Project-URL: Documentation, https://github.com/emews/emews-project-creator#readme
Project-URL: Git Repository, https://github.com/emews/emews-project-creator
Classifier: Development Status :: 4 - Beta
Classifier: Intended Audience :: Science/Research
Classifier: License :: OSI Approved :: BSD License
Classifier: Operating System :: POSIX :: Linux
Classifier: Operating System :: MacOS
Classifier: Operating System :: Microsoft :: Windows
Classifier: Programming Language :: Python :: 3
Classifier: Topic :: Scientific/Engineering
Classifier: Topic :: System :: Distributed Computing
Requires-Python: >=3.7
License-File: LICENSE
Requires-Dist: cookiecutter
Requires-Dist: click
Requires-Dist: pyyaml
Requires-Dist: eqsql
Requires-Dist: colorama
